masha/__init__.py
masha/cli.py
masha/config_loader.py
masha/config_validator.py
masha/env_loader.py
masha/filters/string_utils.py
masha/logger_factory.py
masha/logging.conf
masha/template_renderer.py
masha/tests/maths_utils.py
masha/version.py
masha-0.0.5.dist-info/LICENSE
masha-0.0.5.dist-info/METADATA
masha-0.0.5.dist-info/WHEEL
masha-0.0.5.dist-info/entry_points.txt
masha-0.0.5.dist-info/RECORD
