Metadata-Version: 2.1
Name: masha
Version: 0.0.5
Summary: MASHup of Configuration Loading from several file types and run yAsha like Jinja2 template rendition with Validation
License: Apache-2.0
Author: Mitesh Jat
Author-email: mitesh.singh.jat@gmail.com
Requires-Python: >=3.13,<4.0
Classifier: License :: OSI Approved :: Apache Software License
Classifier: Programming Language :: Python :: 3
Classifier: Programming Language :: Python :: 3.13
Requires-Dist: Jinja2 (>=3.1.5,<4.0.0)
Requires-Dist: click (>=8.1.8,<9.0.0)
Requires-Dist: pydantic (>=2.10.6,<3.0.0)
Requires-Dist: pyyaml (==6.0.2)
Requires-Dist: result (>=0.17.0,<0.18.0)
Requires-Dist: returns (>=0.24.0,<0.25.0)
Requires-Dist: toml (==0.10.2)
